sal_timer/__init__.py
sal_timer-0.0.1.dist-info/LICENSE
sal_timer-0.0.1.dist-info/METADATA
sal_timer-0.0.1.dist-info/WHEEL
sal_timer-0.0.1.dist-info/top_level.txt
sal_timer-0.0.1.dist-info/RECORD
